mcp_k8s_tools/__init__.py
mcp_k8s_tools/server.py
mcp_k8s_tools-0.1.3.dist-info/METADATA
mcp_k8s_tools-0.1.3.dist-info/WHEEL
mcp_k8s_tools-0.1.3.dist-info/entry_points.txt
mcp_k8s_tools-0.1.3.dist-info/top_level.txt
mcp_k8s_tools-0.1.3.dist-info/RECORD
